batchpath.py
batchpath-0.2.dist-info/RECORD
batchpath-0.2.dist-info/METADATA
batchpath-0.2.dist-info/top_level.txt
batchpath-0.2.dist-info/DESCRIPTION.rst
batchpath-0.2.dist-info/WHEEL
batchpath-0.2.dist-info/metadata.json
