Metadata-Version: 2.0
Name: batchpath
Version: 0.2
Summary: Developer utility to generate and verify pathnames
Home-page: https://github.com/brbsix/python-batchpath
Author: Brian Beffa
Author-email: brbsix@gmail.com
License: GPLv3
Keywords: os.walk,pathnames,paths
Platform: UNKNOWN
Classifier: Development Status :: 4 - Beta
Classifier: Environment :: Console
Classifier: Intended Audience :: Developers
Classifier: License :: OSI Approved :: GNU General Public License v3 (GPLv3)
Classifier: Operating System :: POSIX
Classifier: Operating System :: POSIX :: Linux
Classifier: Programming Language :: Python :: 3
Classifier: Programming Language :: Python :: 3.0
Classifier: Programming Language :: Python :: 3.1
Classifier: Programming Language :: Python :: 3.2
Classifier: Programming Language :: Python :: 3.3
Classifier: Programming Language :: Python :: 3.4
Classifier: Programming Language :: Python :: 3 :: Only
Classifier: Topic :: Software Development
Classifier: Topic :: System :: Filesystems
Classifier: Topic :: Utilities
